{"user_id_str": "236511574", "tweet": {"followers": 27522, "tweet": "Pres @jeffabernathy of my alma mater @almacollege is working w colleges in MI to support veterans seeking degrees,\u2026 https://t.co/SLW9PZhTzq", "is_retweet": false, "location": null, "tweet_id": "857368669357314048", "created_at": "Wed Apr 26 22:59:54 +0000 2017", "user_name": "SenGaryPeters", "friends": 1139}},

{"user_id_str": "825359465826353153", "tweet": {"followers": 402, "tweet": "RT @SenGaryPeters: Pres @jeffabernathy of my alma mater @almacollege is working w colleges in MI to support veterans seeking degrees,\u2026 ", "is_retweet": false, "location": "global", "tweet_id": "857368704933298178", "created_at": "Wed Apr 26 23:00:03 +0000 2017", "user_name": "All100Senators", "friends": 100}},

